esgetfamily
