Metadata-Version: 1.1
Name: esgetfamily
Version: 0.5
Summary: Fetch Parent and Child documents in Elasticsearch
Home-page: https://github.com/plotlabs/esgetfamily-python.git
Author: Nayan Jain
Author-email: nayanjain1994@gmail.com
License: LICENSE.txt
Keywords: elasticsearch,elastic-search,parent_child_single_result,es combined result,join type result,parent child,join type result,parent child,parent child single result,elasticsearch parent child
Platform: UNKNOWN
Classifier: Programming Language :: Python :: 2.7
